ion_CSP/__init__.py
ion_CSP/__main__.py
ion_CSP/convert_SMILES.py
ion_CSP/empirical_estimate.py
ion_CSP/gen_opt.py
ion_CSP/identify_molecules.py
ion_CSP/log_and_time.py
ion_CSP/mlp_opt.py
ion_CSP/read_mlp_density.py
ion_CSP/task_manager.py
ion_CSP/vasp_processing.py
ion_CSP/model/model.pt
ion_CSP/model/options/README.md
ion_CSP/model/options/model.ckpt-4000000.pt
ion_CSP/param/INCAR_0
ion_CSP/param/INCAR_1
ion_CSP/param/INCAR_2
ion_CSP/param/INCAR_3
ion_CSP/param/POTCAR_C
ion_CSP/param/POTCAR_H
ion_CSP/param/POTCAR_N
ion_CSP/param/POTCAR_O
ion_CSP/param/g16_sub.sh
ion_CSP/param/sub_final.sh
ion_CSP/param/sub_ori.sh
ion_CSP/param/sub_supple.sh
ion_CSP/run/__init__.py
ion_CSP/run/main_CSP.py
ion_CSP/run/main_EE.py
ion_CSP/run/run_convert_SMILES.py
ion_CSP/run/run_empirical_estimate.py
ion_CSP/run/run_gen_opt.py
ion_CSP/run/run_read_mlp_density.py
ion_CSP/run/run_upload_download.py
ion_CSP/run/run_vasp_processing.py
ion_csp-2.2.6.dist-info/licenses/LICENSE
ion_csp-2.2.6.dist-info/METADATA
ion_csp-2.2.6.dist-info/WHEEL
ion_csp-2.2.6.dist-info/entry_points.txt
ion_csp-2.2.6.dist-info/top_level.txt
ion_csp-2.2.6.dist-info/RECORD
