Metadata-Version: 2.4
Name: ion_CSP
Version: 2.2.6
Summary: Crystal Structure Design Software Based on Molecular/Ionic Configuration.
Home-page: https://github.com/bagabaga007/ion_CSP
Author: Ze Yang
Author-email: Ze Yang <yangze1995007@163.com>
License: MIT
Keywords: Ion_Crystal, Crystal_Structure_Prediction
Classifier: Programming Language :: Python :: 3
Classifier: Operating System :: OS Independent
Requires-Python: >=3.11
License-File: LICENSE
Requires-Dist: ase==3.23.0
Requires-Dist: scipy==1.15.2
Requires-Dist: deepmd-kit==3.0.1
Requires-Dist: torch==2.5.0
Requires-Dist: dpdispatcher==0.6.7
Requires-Dist: numpy==1.26.4
Requires-Dist: paramiko==3.5.1
Requires-Dist: pyxtal==1.0.4
Requires-Dist: phonopy==2.28.0
Requires-Dist: rdkit==2024.3.3
Requires-Dist: pytest==8.3.4
Dynamic: author
Dynamic: home-page
Dynamic: license-file
Dynamic: requires-python
